ndastro_engine/ayanamsa.py
ndastro_engine/config.py
ndastro_engine/constants.py
ndastro_engine/core.py
ndastro_engine/enums.py
ndastro_engine/house_enum.py
ndastro_engine/models.py
ndastro_engine/nakshatra_enum.py
ndastro_engine/planet_enum.py
ndastro_engine/rasi_enum.py
ndastro_engine/utils.py
ndastro_engine-0.8.1.dist-info/METADATA
ndastro_engine-0.8.1.dist-info/WHEEL
ndastro_engine-0.8.1.dist-info/licenses/LICENSE
ndastro_engine-0.8.1.dist-info/RECORD
