Metadata-Version: 2.4
Name: ndastro-engine
Version: 0.8.1
Summary: A modern Vedic astrology calculation engine for Python, providing accurate astronomical calculations for birth charts, planetary positions, and ayanamsa systems.
License: MIT
License-File: LICENSE
Keywords: astronomy,vedic astrology,south indian astrology,north indian astrology,astro,skyfield,astronomical-calculations,birth-chart,horoscope
Author: Jaganathan, B
Author-email: jaganathan.eswaran@gmail.com
Maintainer: Jaganathan, B
Maintainer-email: jaganathan.eswaran@gmail.com
Requires-Python: >=3.10,<4.0
Classifier: Development Status :: 3 - Alpha
Classifier: Intended Audience :: Developers
Classifier: Intended Audience :: Science/Research
Classifier: License :: OSI Approved :: MIT License
Classifier: Operating System :: OS Independent
Classifier: Programming Language :: Python :: 3
Classifier: Programming Language :: Python :: 3.10
Classifier: Programming Language :: Python :: 3.11
Classifier: Programming Language :: Python :: 3.12
Classifier: Programming Language :: Python :: 3.13
Classifier: Topic :: Scientific/Engineering :: Astronomy
Classifier: Topic :: Software Development :: Libraries :: Python Modules
Classifier: Typing :: Typed
Provides-Extra: dev
Provides-Extra: docs
Requires-Dist: mkdocs (>=1.5.0) ; extra == "docs"
Requires-Dist: mkdocs-material (>=9.5.0) ; extra == "docs"
Requires-Dist: mkdocstrings[python] (>=0.24.0) ; extra == "docs"
Requires-Dist: mypy (>=1.19.1) ; extra == "dev"
Requires-Dist: pymdown-extensions (>=10.7.0) ; extra == "docs"
Requires-Dist: pytest (>=9.0.2) ; extra == "dev"
Requires-Dist: pytest-cov (>=6.0.0) ; extra == "dev"
Requires-Dist: pytest-xdist (>=3.6.1) ; extra == "dev"
Requires-Dist: pytz (>=2025.2,<2026.0)
Requires-Dist: ruff (>=0.14.10) ; extra == "dev"
Requires-Dist: skyfield (>=1.53,<2.0)
Project-URL: Bug Tracker, https://github.com/jaganathanb/ndastro-core/issues
Project-URL: Changelog, https://github.com/jaganathanb/ndastro-core/releases
Project-URL: Documentation, https://dhuruvah-apps.github.io/ndastro-core/
Project-URL: Homepage, https://dhuruvah-apps.github.io/ndastro-core/
Project-URL: Repository, https://github.com/jaganathanb/ndastro-core
